MANIFEST.in
README.md
setup.cfg
setup.py
redteam/EDB.py
redteam/IncludeFuncs.py
redteam/RedTeamTrello.py
redteam/SAPI.py
redteam/__init__.py
redteam/redteam.py
redteam.egg-info/PKG-INFO
redteam.egg-info/SOURCES.txt
redteam.egg-info/dependency_links.txt
redteam.egg-info/requires.txt
redteam.egg-info/top_level.txt
redteam/defaults/trello.tar.gz