Metadata-Version: 1.1
Name: redteam
Version: 0.3.5
Summary: Red team SDK for Python.
Home-page: https://github.com/fedoraredteam/python-sdk
Author: Jason Callaway
Author-email: jasoncallaway@fedoraproject.org
License: GPLv2
Download-URL: https://github.com/fedoraredteam/python-sdk/archive/v0.3.5.tar.gz
Keywords: cve,exploit,linux,red team,pen testing
Platform: Linux
Classifier: Development Status :: 4 - Beta
Classifier: License :: OSI Approved :: GNU General Public License v2 (GPLv2)
Classifier: Programming Language :: Python :: 2.7
